template_profiler_panel/__init__.py
template_profiler_panel/apps.py
template_profiler_panel/panels/__init__.py
template_profiler_panel/panels/template.py
template_profiler_panel/templates/template_profiler_panel/template.html
template_profiler_panel/templatetags/__init__.py
template_profiler_panel/templatetags/template_profiler.py
template_profiler_panel/tests/__init__.py
template_profiler_panel/tests/dummy_settings.py
template_profiler_panel/tests/test_template.py
django_debug_toolbar_template_profiler-2.1.0.dist-info/LICENSE
django_debug_toolbar_template_profiler-2.1.0.dist-info/METADATA
django_debug_toolbar_template_profiler-2.1.0.dist-info/WHEEL
django_debug_toolbar_template_profiler-2.1.0.dist-info/top_level.txt
django_debug_toolbar_template_profiler-2.1.0.dist-info/RECORD
