Metadata-Version: 2.1
Name: django-debug-toolbar-template-profiler
Version: 2.1.0
Summary: Displays template rendering time on the timeline
Home-page: https://github.com/node13h/django-debug-toolbar-template-profiler
Author: Sergej Alikov
Author-email: sergej.alikov@gmail.com
Maintainer: Adam Johnson
Maintainer-email: me@adamj.eu
License: Simplified BSD License
Project-URL: Changelog, https://github.com/node13h/django-debug-toolbar-template-profiler/blob/master/HISTORY.rst
Platform: UNKNOWN
Classifier: Development Status :: 5 - Production/Stable
Classifier: Environment :: Web Environment
Classifier: Framework :: Django
Classifier: Intended Audience :: Developers
Classifier: License :: OSI Approved :: BSD License
Classifier: Operating System :: OS Independent
Classifier: Programming Language :: Python
Classifier: Programming Language :: Python :: 2
Classifier: Programming Language :: Python :: 2.7
Classifier: Programming Language :: Python :: 3
Classifier: Topic :: Software Development :: Libraries :: Python Modules
License-File: LICENSE
